PC.v
module PC(In, Out, Clk);
    	input [31:0] In;
    	input Clk;
    	output reg[31:0] Out;
		reg [31:0] PC = 0;
    	reg count = 0;
	always @(posedge Clk)
	begin
    		PC = In;
    		if (count == 0)	begin
        		Out = 0;				//initally PC is set to zero
        		count = 1;
    		end
    		else begin
    			Out = PC;        
    		end
	end    
endmodule

Mux.v
module Mux(In1, In2, Out, Sel);
	parameter S = 31;
	input [S:0] In1, In2;
    input Sel;
    output reg [S:0] Out;

	always @(Sel or In1 or In2)
	begin    
    	case (Sel)
        	0 : Out = In1;
        	1 : Out = In2;
    	endcase
	end
endmodule

Mux_5_bit.v
module Mux_5_bit(In1, In2, Out, Sel);
	parameter S = 4;
    input [S:0] In1, In2;
    input Sel;
    output reg [S:0] Out;
	
	always @(Sel or In1 or In2) 
	begin    
    		case (Sel)
        		0 : Out = In1;
        		1 : Out = In2;
    		endcase
	end
endmodule

Sign_extender.v
module Sign_extender (In, Out, Clk);
	input [15:0] In;
    	input Clk;
	output [31:0] Out;
    	assign Out = $signed(In);    
endmodule

Data_Memory.v
module Data_memory(A, WD, WE, RD);
	input [31:0]A,WD;
	input WE;
	output reg [31:0]RD;
	reg [7:0]Memory[0:1];
	initial
        	$readmemb("init_data_mem.dat",Memory);
	always @(A or WD or WE) begin
		if(WE==1'b0) begin				//Read 4 consecutive lines from the memory
			Memory[A]=WD[7:0];
			Memory[A+1]=WD[15:8];
			Memory[A+2]=WD[23:16];
			Memory[A+3]=WD[31:24];
		end
		if(WE==1'b1) begin				//Write 4 consecutive line in the memory
			RD={Memory[A],Memory[A+1],Memory[A+2],Memory[A+3]};
		end
	end
endmodule

ALU.v
module ALU(SrcA, SrcB, ALUSec, ALU_result, Zero);
	input [31:0] SrcA;
	input [31:0] SrcB;
	input [2:0] ALUSec;

	output reg [31:0] ALU_result;
	output reg Zero;

	always @(SrcA or SrcB or ALUSec) begin
		Zero=0;
		if(ALUSec==0) begin				//And
			ALU_result=SrcA & SrcB;
		end
		if(ALUSec==1) begin				//Or
			ALU_result=SrcA | SrcB;
		end
		if(ALUSec==2) begin				//Add
			ALU_result=SrcA+SrcB;
		end
		if(ALUSec==3) begin				//Subtract
			ALU_result=SrcA-SrcB;
			if(ALU_result==0) begin		//Beq
				Zero<=1;
			end
			else begin
				Zero<=0;
			end
		end
		if(ALUSec==4) begin				//Set on less than
			if(SrcA<SrcB) begin
				ALU_result <= 1;
			end
			if(SrcA>=SrcB) begin
				ALU_result <= 0;
			end
		end
	end
endmodule

ALU_control_unit.v
module ALU_control_unit(ALU_Op, Function, ALU_control);
	input [1:0] ALU_Op;
	input [5:0] Function;
	output reg[2:0] ALU_control;

	always @(ALU_Op or Function)
	begin
		if(ALU_Op==0) begin				//Load Word
			ALU_control=2;
		end
		if(ALU_Op==1) begin				//BEQ
			ALU_control=3;
		end
		if(ALU_Op==2) begin				//R-Instructions
			if(Function==32) begin		//Add
				ALU_control=2;
			end
			if(Function==34) begin		//sub
				ALU_control=3;
			end
			if(Function==36) begin		//And
				ALU_control=0;
			end
			if(Function==37) begin		//Or	
				ALU_control=1;
			end
			if(Function==42) begin		//Set on less than
				ALU_control=4;
			end
		end
	end
endmodule

Control_unit.v
module Control_unit(Op, Mem_reg, Mem_write, Branch, ALU_Op, ALU_src, Reg_dst, Reg_write, Jump, Clk);
	input [5:0] Op;
    	input Clk;
    	output reg Mem_reg, Mem_write, Branch, ALU_src, Reg_dst, Reg_write, Jump;
    	output reg [1:0] ALU_Op;
	
    	always @(Op or posedge Clk)

	//more instructions can be added below

	begin					
        case(Op)
        6'b000000:                //R-instructions
        begin
            	Reg_dst=1;
            	ALU_src=0;
            	Mem_reg=0;
            	Reg_write=0;
            	Mem_write=0;
            	Branch=0;
            	ALU_Op=2;
            	Jump=0;
        end
        6'b001000:				//Addi- I instruction
        begin
            	Reg_dst=0;
            	ALU_src=1;
            	Mem_reg=0;
            	Reg_write=0;
            	Mem_write=0;
           	Branch=0;
            	ALU_Op=0;
            	Jump=0;
        end
        6'b100011:             //Load Word
        begin
            	Reg_dst=0;
            	ALU_src=1;
            	Mem_reg=1;
            	Reg_write=0;
            	Mem_write=0;
            	Branch=0;
            	ALU_Op=0;
            	Jump=0;
        end
        6'b101011:             //Store Word
        begin
            	Reg_dst=0;
            	ALU_src=1;
            	Mem_reg=0;
            	Reg_write=1;
            	Mem_write=1;
            	Branch=0;
            	ALU_Op=0;
            	Jump=0;
        end
        6'b000100:             //BEQ
        begin
            	Reg_dst=0;
            	ALU_src=0;
            	Mem_reg=0;
            	Reg_write=1;
            	Mem_write=1;
            	Branch=1;
            	ALU_Op=1;
            	Jump=0;
        end
        6'b000010:             //Jump
        begin
            	Reg_dst=0;
            	ALU_src=0;
            	Mem_reg=0;
            	Reg_write=1;
            	Mem_write=0;
            	Branch=0;
            	ALU_Op=0;
            	Jump=1;
        end
        endcase
    end
endmodule

Registers.v
module Registers(A1, A2, A3, WD3, RD1, RD2, WE3);
	input [4:0] A1, A2, A3;
	input [31:0] WD3;
	input WE3;
	output reg [31:0] RD1, RD2;
	reg [31:0] Reg[0:31];
	reg [4:0] count;
	integer i;

	initial begin				//initalising all the registers to 0
  		count=0;
  		for (i=0;i<=31;i=i+1)
    			Reg[i]=0;
	end
	always @(A1 or A2 or A3 or WD3 or WE3)
	begin
		RD1=Reg[A1];
		RD2=Reg[A2];
		if (WE3 == 0)	begin
			Reg[A3]<=WD3;
		end
	end
endmodule

Instruction_Memory.v
module Instruction_Memory(A, RD);
	input [31:0] A;
	output reg [31:0] RD;
	reg [7:0] Memory[0:59];
	initial
		$readmemb("init.dat",Memory);
	
	always @(A)
	begin			//Read 4 lines from the instruction memory
		RD={Memory[A],Memory[A+1],Memory[A+2],Memory[A+3]};
	end
endmodule

Mips.v
`include "ALU.v"
`include "ALU_control_unit.v"
`include "Instruction_Memory.v"
`include "Registers.v"
`include "Data_Memory.v"
`include "Control_unit.v"
`include "Mux.v"
`include "Sign_extender.v"
`include "Mux_5_bit.v"
`include "PC.v"

module Mips(clk);
	wire Jump, PC_Src;          //Jump--PC_mux_2 switch, PC_Src--PC_mux_1_switch 
	wire [31:0] PC_jump, PC_branch, PC_mux_1_2; //PC_mux_1_2 between mux1 and mux 2
	wire [31:0] PC_1, PC_2; //to PC_reg, out PC_reg
	wire [31:0] PC_plus_4;  //for PC++, from adder
	wire [27:0] PC_slt;//after Instr & shift left to PC_jump
	wire [31:0] Instr;  //out Instr_mem
	wire [31:0] Sign_imm;   //After sign ext
	wire [31:0] Sign_imm_mux; //After let shift to mux
	//wires from Control unit
	wire Reg_write, Reg_dst, ALU_src, Branch, Mem_write, Mem_reg;
	wire [1:0] ALU_Op;
	wire [4:0] Write_reg;
	wire [2:0] ALU_control_wire;
	//wires from Reg_file
	wire [31:0] Src_A, Write_data;
	//wires for ALU
	wire Zero;
	wire [31:0] Src_B, ALU_result;
	//wires from Data memory
	wire [31:0] Read_data;
	//wire after Mem to Reg Mux
	wire [31:0] Result;
	input clk;
	reg [31:0] Reg;
	Instruction_Memory instr_mem_unit (
    		.A(PC_2),
    		.RD(Instr)
	);
	Registers register_file_unit (
    		.RD1(Src_A),                //3 inputs 
    		.RD2(Write_data),
    		.A3(Write_reg),      
    		.WE3(Reg_write),            //enable from control
    		.WD3(Result),               //data from alu/memory
    		.A1(Instr[25:21]),          //Reg to ALU
    		.A2(Instr[20:16])           //to ALU/memory
	);
	Control_unit control_unit (
    		.Op(Instr[31:26]),          //OP code        
    		.Mem_reg(Mem_reg),          //Mem to Register file mux
    		.Mem_write(Mem_write),      //Memory Enable
    		.Branch(Branch),            
    		.ALU_Op(ALU_Op),  	    //ALU control
    		.ALU_src(ALU_src),          //mux for regfile to alu/memory
    		.Reg_dst(Reg_dst),          //mux for A3 in reg file
    		.Reg_write(Reg_write),      //reg write enable
    		.Jump(Jump),                
    		.Clk(clk)
	);
	ALU_control_unit alu_control_unit (
    		.ALU_Op(ALU_Op),
    		.Function(Instr[5:0]),
    		.ALU_control(ALU_control_wire)
	);
	ALU alu_unit (
    		.SrcA(Src_A),           //input A for ALU
    		.SrcB(Src_B),           //input B for ALU
    		.ALUSec(ALU_control_wire),   //ALU Select
    		.Zero(Zero),            
    		.ALU_result(ALU_result)
	);
	Data_memory data_mem_unit (
    		.A(ALU_result),     //input from ALU
    		.WD(Write_data),    //input from Reg file
    		.WE(Mem_write),     //memory enable
    		.RD(Read_data)     //memory output
	);
	Sign_extender uut5 (
    		.In(Instr[15:0]),
    		.Out(Sign_imm)
	);
	//Mux_1 before PC 
	Mux uut6(               
    		.In1(PC_plus_4),
    		.In2(PC_branch),
    		.Out(PC_mux_1_2),
    		.Sel(PC_Src)
	);
	//Mux_2 before PC
	Mux uut7(               
    		.In1(PC_mux_1_2),
    		.In2(PC_jump),
    		.Out(PC_1),
    		.Sel(Jump)
	);
	//Mux before ALU
	Mux uut8(               
    		.In1(Write_data),
    		.In2(Sign_imm),
    		.Out(Src_B),
    		.Sel(ALU_src)
	);
	//Mux for Reg file, for R format instructions
	Mux_5_bit uut9 (        
    		.In1(Instr[20:16]),
    		.In2(Instr[15:11]),
    		.Out(Write_reg),
    		.Sel(Reg_dst)
	);
	//Mux after ALU/Data_Memory
	Mux uut10(              
    		.In1(ALU_result),
    		.In2(Read_data),
    		.Out(Result),
    		.Sel(Mem_reg)
	);
	PC pc_unit(
    		.In(PC_1),
    		.Out(PC_2),
    		.Clk(clk)
	);
	assign PC_plus_4 = PC_2 + 4;
	assign PC_branch = PC_plus_4+(Sign_imm << 2);
	assign PC_slt = Instr << 2;
	assign PC_jump = {PC_plus_4[31:28],PC_slt};
	assign PC_Src = (Branch & Zero);
endmodule

main.v
`timescale 1ns/1ps
`include "Mips.v"

//This Mips processor is based on the slides discussed in the class

//main contains the clock and calls the module Mips
//All the modules and connections are initialised in Mips.v

module main(clk);
	output reg clk = 0;
	Mips uut (
    		.clk(clk)
	);

	always #5 clk = ~ clk;
	initial begin 
		$dumpfile("Mips.vcd");
		$dumpvars(0,main);
	end    
endmodule

Mips.vcd
$date
	Sat Dec  7 07:04:27 2019
$end
$version
	Icarus Verilog
$end
$timescale
	1ps
$end
$scope module main $end
$var reg 1 ! clk $end
$scope module uut $end
$var wire 1 " PC_Src $end
$var wire 1 ! clk $end
$var wire 1 # Zero $end
$var wire 5 $ Write_reg [4:0] $end
$var wire 32 % Write_data [31:0] $end
$var wire 32 & Src_B [31:0] $end
$var wire 32 ' Src_A [31:0] $end
$var wire 32 ( Sign_imm [31:0] $end
$var wire 32 ) Result [31:0] $end
$var wire 1 * Reg_write $end
$var wire 1 + Reg_dst $end
$var wire 32 , Read_data [31:0] $end
$var wire 28 - PC_slt [27:0] $end
$var wire 32 . PC_plus_4 [31:0] $end
$var wire 32 / PC_mux_1_2 [31:0] $end
$var wire 32 0 PC_jump [31:0] $end
$var wire 32 1 PC_branch [31:0] $end
$var wire 32 2 PC_2 [31:0] $end
$var wire 32 3 PC_1 [31:0] $end
$var wire 1 4 Mem_write $end
$var wire 1 5 Mem_reg $end
$var wire 1 6 Jump $end
$var wire 32 7 Instr [31:0] $end
$var wire 1 8 Branch $end
$var wire 1 9 ALU_src $end
$var wire 32 : ALU_result [31:0] $end
$var wire 3 ; ALU_control_wire [2:0] $end
$var wire 2 < ALU_Op [1:0] $end
$scope module alu_control_unit $end
$var wire 6 = Function [5:0] $end
$var wire 2 > ALU_Op [1:0] $end
$var reg 3 ? ALU_control [2:0] $end
$upscope $end
$scope module alu_unit $end
$var wire 3 @ ALUSec [2:0] $end
$var wire 32 A SrcB [31:0] $end
$var wire 32 B SrcA [31:0] $end
$var reg 32 C ALU_result [31:0] $end
$var reg 1 # Zero $end
$upscope $end
$scope module control_unit $end
$var wire 1 ! Clk $end
$var wire 6 D Op [5:0] $end
$var reg 2 E ALU_Op [1:0] $end
$var reg 1 9 ALU_src $end
$var reg 1 8 Branch $end
$var reg 1 6 Jump $end
$var reg 1 5 Mem_reg $end
$var reg 1 4 Mem_write $end
$var reg 1 + Reg_dst $end
$var reg 1 * Reg_write $end
$upscope $end
$scope module data_mem_unit $end
$var wire 32 F A [31:0] $end
$var wire 1 4 WE $end
$var wire 32 G WD [31:0] $end
$var reg 32 H RD [31:0] $end
$upscope $end
$scope module instr_mem_unit $end
$var wire 32 I A [31:0] $end
$var reg 32 J RD [31:0] $end
$upscope $end
$scope module pc_unit $end
$var wire 1 ! Clk $end
$var wire 32 K In [31:0] $end
$var reg 32 L Out [31:0] $end
$var reg 32 M PC [31:0] $end
$var reg 1 N count $end
$upscope $end
$scope module register_file_unit $end
$var wire 5 O A1 [4:0] $end
$var wire 5 P A2 [4:0] $end
$var wire 1 * WE3 $end
$var wire 32 Q WD3 [31:0] $end
$var wire 5 R A3 [4:0] $end
$var reg 32 S RD1 [31:0] $end
$var reg 32 T RD2 [31:0] $end
$var reg 5 U count [4:0] $end
$var integer 32 V i [31:0] $end
$upscope $end
$scope module uut10 $end
$var wire 32 W In1 [31:0] $end
$var wire 32 X In2 [31:0] $end
$var wire 1 5 Sel $end
$var reg 32 Y Out [31:0] $end
$upscope $end
$scope module uut5 $end
$var wire 1 Z Clk $end
$var wire 16 [ In [15:0] $end
$var wire 32 \ Out [31:0] $end
$upscope $end
$scope module uut6 $end
$var wire 32 ] In1 [31:0] $end
$var wire 32 ^ In2 [31:0] $end
$var wire 1 " Sel $end
$var reg 32 _ Out [31:0] $end
$upscope $end
$scope module uut7 $end
$var wire 32 ` In1 [31:0] $end
$var wire 32 a In2 [31:0] $end
$var wire 1 6 Sel $end
$var reg 32 b Out [31:0] $end
$upscope $end
$scope module uut8 $end
$var wire 32 c In1 [31:0] $end
$var wire 32 d In2 [31:0] $end
$var wire 1 9 Sel $end
$var reg 32 e Out [31:0] $end
$upscope $end
$scope module uut9 $end
$var wire 5 f In1 [4:0] $end
$var wire 5 g In2 [4:0] $end
$var wire 1 + Sel $end
$var reg 5 h Out [4:0] $end
$upscope $end
$upscope $end
$upscope $end
$enddefinitions $end
#0
$dumpvars
bx h
bx g
bx f
bx e
bx d
bx c
bx b
bx00 a
bx `
bx _
bx ^
bx ]
bx \
bx [
zZ
bx Y
bx X
bx W
b100000 V
b0 U
bx T
bx S
bx R
bx Q
bx P
bx O
0N
b0 M
bx L
bx K
bx J
bx I
bx H
bx G
bx F
bx E
bx D
bx C
bx B
bx A
bx @
bx ?
bx >
bx =
bx <
bx ;
bx :
x9
x8
bx 7
x6
x5
x4
bx 3
bx 2
bx 1
bx00 0
bx /
bx .
bx00 -
bx ,
x+
x*
bx )
bx (
bx '
bx &
bx %
bx $
x#
x"
0!
$end
#5000
b100 3
b100 K
b100 b
b100 /
b100 _
b100 `
0"
b10 )
b10 Q
b10 Y
b10 :
b10 C
b10 F
b10 W
0#
b100010000000000000000001000 -
b10000 $
b10000 R
b10000 h
b1100 1
b1100 ^
b10 &
b10 A
b10 e
b10 ;
b10 ?
b10 @
06
b0 <
b0 >
b0 E
08
04
0*
05
19
0+
b0 %
b0 G
b0 T
b0 c
b0 '
b0 B
b0 S
b0 g
b10000 f
b10 (
b10 \
b10 d
b10 [
b10 =
b1000 D
b10000 P
b1000 O
b100010000000000000000001000 0
b100010000000000000000001000 a
b100001000100000000000000000010 7
b100001000100000000000000000010 J
1N
b100 .
b100 ]
b0 2
b0 I
b0 L
bx M
1!
#10000
0!
#15000
b111 )
b111 Q
b111 Y
b111 :
b111 C
b111 F
b111 W
b100001010000000000000011100 0
b100001010000000000000011100 a
b100001010000000000000011100 -
b1010 $
b1010 R
b1010 h
b111 &
b111 A
b111 e
b1000 3
b1000 K
b1000 b
b1010 f
b111 (
b111 \
b111 d
b111 [
b111 =
b1010 P
b1000 /
b1000 _
b1000 `
b100001000010100000000000000111 7
b100001000010100000000000000111 J
b100100 1
b100100 ^
b1000 .
b1000 ]
b100 2
b100 I
b100 L
b100 M
1!
#20000
0!
#25000
b1 )
b1 Q
b1 Y
b1 :
b1 C
b1 F
b1 W
b100001111000000000000000100 0
b100001111000000000000000100 a
b100001111000000000000000100 -
b1111 $
b1111 R
b1111 h
b1 &
b1 A
b1 e
b1100 3
b1100 K
b1100 b
b1111 f
b1 (
b1 \
b1 d
b1 [
b1 =
b1111 P
b1100 /
b1100 _
b1100 `
b100001000011110000000000000001 7
b100001000011110000000000000001 J
b10000 1
b10000 ^
b1100 .
b1100 ]
b1000 2
b1000 I
b1000 L
b1000 M
1!
#30000
0!
#35000
b111 )
b111 Q
b111 Y
b111 :
b111 C
b111 F
b111 W
b100001010010010000010000000 0
b100001010010010000010000000 a
b100001010010010000010000000 -
b1001 $
b1001 R
b1001 h
b111 &
b111 A
b111 e
b10 <
b10 >
b10 E
09
1+
b111 %
b111 G
b111 T
b111 c
b10000 3
b10000 K
b10000 b
b1001 g
b1010 f
b100100000100000 (
b100100000100000 \
b100100000100000 d
b100100000100000 [
b100000 =
b0 D
b1010 P
b10000 /
b10000 _
b10000 `
b1000010100100100000100000 7
b1000010100100100000100000 J
b10010000010010000 1
b10010000010010000 ^
b10000 .
b10000 ]
b1100 2
b1100 I
b1100 L
b1100 M
1!
#40000
0!
#45000
b11111111111111111111111111111011 )
b11111111111111111111111111111011 Q
b11111111111111111111111111111011 Y
b11111111111111111111111111111011 :
b11111111111111111111111111111011 C
b11111111111111111111111111111011 F
b11111111111111111111111111111011 W
b1000001001000000000000101000 0
b1000001001000000000000101000 a
b1000001001000000000000101000 -
b11 ;
b11 ?
b11 @
b1 <
b1 >
b1 E
18
14
1*
0+
b10 '
b10 B
b10 S
b10100 3
b10100 K
b10100 b
b0 g
b1001 f
b1010 (
b1010 \
b1010 d
b1010 [
b1010 =
b100 D
b1001 P
b10000 O
b10100 /
b10100 _
b10100 `
b10010000010010000000000001010 7
b10010000010010000000000001010 J
b111100 1
b111100 ^
b10100 .
b10100 ]
b10000 2
b10000 I
b10000 L
b10000 M
1!
#50000
0!
#55000
b110 )
b110 Q
b110 Y
b110 :
b110 C
b110 F
b110 W
b100101111010010000010001000 0
b100101111010010000010001000 a
b100101111010010000010001000 -
b1 &
b1 A
b1 e
b10 <
b10 >
b10 E
08
04
0*
1+
b1 %
b1 G
b1 T
b1 c
b111 '
b111 B
b111 S
b11000 3
b11000 K
b11000 b
b1001 g
b1111 f
b100100000100010 (
b100100000100010 \
b100100000100010 d
b100100000100010 [
b100010 =
b0 D
b1111 P
b1001 O
b11000 /
b11000 _
b11000 `
b1001011110100100000100010 7
b1001011110100100000100010 J
b10010000010100000 1
b10010000010100000 ^
b11000 .
b11000 ]
b10100 2
b10100 I
b10100 L
b10100 M
1!
#60000
0!
#65000
b100101000011000000010000000 0
b100101000011000000010000000 a
b100101000011000000010000000 -
b1100 $
b1100 R
b1100 h
b0 &
b0 A
b0 e
b10 ;
b10 ?
b10 @
b0 %
b0 G
b0 T
b0 c
b110 '
b110 B
b110 S
b11100 3
b11100 K
b11100 b
b1100 g
b1000 f
b110000000100000 (
b110000000100000 \
b110000000100000 d
b110000000100000 [
b100000 =
b1000 P
b11100 /
b11100 _
b11100 `
b1001010000110000000100000 7
b1001010000110000000100000 J
b11000000010011100 1
b11000000010011100 ^
b11100 .
b11100 ]
b11000 2
b11000 I
b11000 L
b11000 M
1!
#70000
0!
#75000
b11111111111111111111111111111010 )
b11111111111111111111111111111010 Q
b11111111111111111111111111111010 Y
b11111111111111111111111111111010 :
b11111111111111111111111111111010 C
b11111111111111111111111111111010 F
b11111111111111111111111111111010 W
b100001100111111111111110000 0
b100001100111111111111110000 a
b100001100111111111111110000 -
b110 &
b110 A
b110 e
b11 ;
b11 ?
b11 @
b1 <
b1 >
b1 E
18
14
1*
0+
b110 %
b110 G
b110 T
b110 c
b0 '
b0 B
b0 S
b100000 3
b100000 K
b100000 b
b11111 g
b1100 f
b11111111111111111111111111111100 (
b11111111111111111111111111111100 \
b11111111111111111111111111111100 d
b1111111111111100 [
b111100 =
b100 D
b1100 P
b1000 O
b100000 /
b100000 _
b100000 `
b10001000011001111111111111100 7
b10001000011001111111111111100 J
b10000 1
b10000 ^
b100000 .
b100000 ]
b11100 2
b11100 I
b11100 L
b11100 M
1!
#80000
0!
#85000
b111 )
b111 Q
b111 Y
b111 :
b111 C
b111 F
b111 W
b110101010011010000010000000 0
b110101010011010000010000000 a
b110101010011010000010000000 -
b1101 $
b1101 R
b1101 h
b111 &
b111 A
b111 e
b10 ;
b10 ?
b10 @
b10 <
b10 >
b10 E
08
04
0*
1+
b111 %
b111 G
b111 T
b111 c
b100100 3
b100100 K
b100100 b
b1101 g
b1010 f
b110100000100000 (
b110100000100000 \
b110100000100000 d
b110100000100000 [
b100000 =
b0 D
b1010 P
b1101 O
b100100 /
b100100 _
b100100 `
b1101010100110100000100000 7
b1101010100110100000100000 J
b11010000010100100 1
b11010000010100100 ^
b100100 .
b100100 ]
b100000 2
b100000 I
b100000 L
b100000 M
1!
#90000
0!
#95000
b101 )
b101 Q
b101 Y
b101 :
b101 C
b101 F
b101 W
b110001111011000000010001000 0
b110001111011000000010001000 a
b110001111011000000010001000 -
b1100 $
b1100 R
b1100 h
b1 &
b1 A
b1 e
b11 ;
b11 ?
b11 @
b1 %
b1 G
b1 T
b1 c
b110 '
b110 B
b110 S
b101000 3
b101000 K
b101000 b
b1100 g
b1111 f
b110000000100010 (
b110000000100010 \
b110000000100010 d
b110000000100010 [
b100010 =
b1111 P
b1100 O
b101000 /
b101000 _
b101000 `
b1100011110110000000100010 7
b1100011110110000000100010 J
b11000000010110000 1
b11000000010110000 ^
b101000 .
b101000 ]
b100100 2
b100100 I
b100100 L
b100100 M
1!
#100000
0!
#105000
b11111111111111111111111111111011 )
b11111111111111111111111111111011 Q
b11111111111111111111111111111011 Y
b11111111111111111111111111111011 :
b11111111111111111111111111111011 C
b11111111111111111111111111111011 F
b11111111111111111111111111111011 W
b100001100000000000000000100 0
b100001100000000000000000100 a
b100001100000000000000000100 -
b101 &
b101 A
b101 e
b1 <
b1 >
b1 E
18
14
1*
0+
b101 %
b101 G
b101 T
b101 c
b0 '
b0 B
b0 S
b101100 3
b101100 K
b101100 b
b0 g
b1100 f
b1 (
b1 \
b1 d
b1 [
b1 =
b100 D
b1100 P
b1000 O
b101100 /
b101100 _
b101100 `
b10001000011000000000000000001 7
b10001000011000000000000000001 J
b110000 1
b110000 ^
b101100 .
b101100 ]
b101000 2
b101000 I
b101000 L
b101000 M
1!
#110000
0!
#115000
b0 )
b0 Q
b0 Y
b0 :
b0 C
b0 F
b0 W
b11100 0
b11100 a
b11100 -
b0 $
b0 R
b0 h
b0 &
b0 A
b0 e
b10 ;
b10 ?
b10 @
16
b0 <
b0 >
b0 E
08
04
b0 %
b0 G
b0 T
b0 c
b11100 3
b11100 K
b11100 b
b0 f
b111 (
b111 \
b111 d
b111 [
b111 =
b10 D
b0 P
b0 O
b110000 /
b110000 _
b110000 `
b1000000000000000000000000111 7
b1000000000000000000000000111 J
b1001100 1
b1001100 ^
b110000 .
b110000 ]
b101100 2
b101100 I
b101100 L
b101100 M
1!
#120000
0!
#125000
b11111111111111111111111111111011 )
b11111111111111111111111111111011 Q
b11111111111111111111111111111011 Y
b11111111111111111111111111111011 :
b11111111111111111111111111111011 C
b11111111111111111111111111111011 F
b11111111111111111111111111111011 W
b100000 3
b100000 K
b100000 b
bx ,
bx H
bx X
b100001100111111111111110000 0
b100001100111111111111110000 a
b100001100111111111111110000 -
b1100 $
b1100 R
b1100 h
b101 &
b101 A
b101 e
b11 ;
b11 ?
b11 @
06
b1 <
b1 >
b1 E
18
14
b101 %
b101 G
b101 T
b101 c
b11111 g
b1100 f
b11111111111111111111111111111100 (
b11111111111111111111111111111100 \
b11111111111111111111111111111100 d
b1111111111111100 [
b111100 =
b100 D
b1100 P
b1000 O
b100000 /
b100000 _
b100000 `
b10001000011001111111111111100 7
b10001000011001111111111111100 J
b10000 1
b10000 ^
b100000 .
b100000 ]
b11100 2
b11100 I
b11100 L
b11100 M
1!
#130000
0!
#135000
b1110 )
b1110 Q
b1110 Y
b1110 :
b1110 C
b1110 F
b1110 W
b110101010011010000010000000 0
b110101010011010000010000000 a
b110101010011010000010000000 -
b1101 $
b1101 R
b1101 h
b111 &
b111 A
b111 e
b10 ;
b10 ?
b10 @
b10 <
b10 >
b10 E
08
04
0*
1+
b111 %
b111 G
b111 T
b111 c
b111 '
b111 B
b111 S
b100100 3
b100100 K
b100100 b
b1101 g
b1010 f
b110100000100000 (
b110100000100000 \
b110100000100000 d
b110100000100000 [
b100000 =
b0 D
b1010 P
b1101 O
b100100 /
b100100 _
b100100 `
b1101010100110100000100000 7
b1101010100110100000100000 J
b11010000010100100 1
b11010000010100100 ^
b100100 .
b100100 ]
b100000 2
b100000 I
b100000 L
b100000 M
1!
#140000
0!
#145000
b100 )
b100 Q
b100 Y
b100 :
b100 C
b100 F
b100 W
b110001111011000000010001000 0
b110001111011000000010001000 a
b110001111011000000010001000 -
b1100 $
b1100 R
b1100 h
b1 &
b1 A
b1 e
b11 ;
b11 ?
b11 @
b1 %
b1 G
b1 T
b1 c
b101 '
b101 B
b101 S
b101000 3
b101000 K
b101000 b
b1100 g
b1111 f
b110000000100010 (
b110000000100010 \
b110000000100010 d
b110000000100010 [
b100010 =
b1111 P
b1100 O
b101000 /
b101000 _
b101000 `
b1100011110110000000100010 7
b1100011110110000000100010 J
b11000000010110000 1
b11000000010110000 ^
b101000 .
b101000 ]
b100100 2
b100100 I
b100100 L
b100100 M
1!
#150000
0!
#155000
b11111111111111111111111111111100 )
b11111111111111111111111111111100 Q
b11111111111111111111111111111100 Y
b11111111111111111111111111111100 :
b11111111111111111111111111111100 C
b11111111111111111111111111111100 F
b11111111111111111111111111111100 W
b100001100000000000000000100 0
b100001100000000000000000100 a
b100001100000000000000000100 -
b100 &
b100 A
b100 e
b1 <
b1 >
b1 E
18
14
1*
0+
b100 %
b100 G
b100 T
b100 c
b0 '
b0 B
b0 S
b101100 3
b101100 K
b101100 b
b0 g
b1100 f
b1 (
b1 \
b1 d
b1 [
b1 =
b100 D
b1100 P
b1000 O
b101100 /
b101100 _
b101100 `
b10001000011000000000000000001 7
b10001000011000000000000000001 J
b110000 1
b110000 ^
b101100 .
b101100 ]
b101000 2
b101000 I
b101000 L
b101000 M
1!
#160000
0!
#165000
b0 )
b0 Q
b0 Y
b0 :
b0 C
b0 F
b0 W
b11100 0
b11100 a
b11100 -
b0 $
b0 R
b0 h
b0 &
b0 A
b0 e
b10 ;
b10 ?
b10 @
16
b0 <
b0 >
b0 E
08
04
b0 %
b0 G
b0 T
b0 c
b11100 3
b11100 K
b11100 b
b0 f
b111 (
b111 \
b111 d
b111 [
b111 =
b10 D
b0 P
b0 O
b110000 /
b110000 _
b110000 `
b1000000000000000000000000111 7
b1000000000000000000000000111 J
b1001100 1
b1001100 ^
b110000 .
b110000 ]
b101100 2
b101100 I
b101100 L
b101100 M
1!
#170000
0!
#175000
b11111111111111111111111111111100 )
b11111111111111111111111111111100 Q
b11111111111111111111111111111100 Y
b11111111111111111111111111111100 :
b11111111111111111111111111111100 C
b11111111111111111111111111111100 F
b11111111111111111111111111111100 W
b100000 3
b100000 K
b100000 b
bx ,
bx H
bx X
b100001100111111111111110000 0
b100001100111111111111110000 a
b100001100111111111111110000 -
b1100 $
b1100 R
b1100 h
b100 &
b100 A
b100 e
b11 ;
b11 ?
b11 @
06
b1 <
b1 >
b1 E
18
14
b100 %
b100 G
b100 T
b100 c
b11111 g
b1100 f
b11111111111111111111111111111100 (
b11111111111111111111111111111100 \
b11111111111111111111111111111100 d
b1111111111111100 [
b111100 =
b100 D
b1100 P
b1000 O
b100000 /
b100000 _
b100000 `
b10001000011001111111111111100 7
b10001000011001111111111111100 J
b10000 1
b10000 ^
b100000 .
b100000 ]
b11100 2
b11100 I
b11100 L
b11100 M
1!
#180000
0!
#185000
b10101 )
b10101 Q
b10101 Y
b10101 :
b10101 C
b10101 F
b10101 W
b110101010011010000010000000 0
b110101010011010000010000000 a
b110101010011010000010000000 -
b1101 $
b1101 R
b1101 h
b111 &
b111 A
b111 e
b10 ;
b10 ?
b10 @
b10 <
b10 >
b10 E
08
04
0*
1+
b111 %
b111 G
b111 T
b111 c
b1110 '
b1110 B
b1110 S
b100100 3
b100100 K
b100100 b
b1101 g
b1010 f
b110100000100000 (
b110100000100000 \
b110100000100000 d
b110100000100000 [
b100000 =
b0 D
b1010 P
b1101 O
b100100 /
b100100 _
b100100 `
b1101010100110100000100000 7
b1101010100110100000100000 J
b11010000010100100 1
b11010000010100100 ^
b100100 .
b100100 ]
b100000 2
b100000 I
b100000 L
b100000 M
1!
#190000
0!
#195000
b11 )
b11 Q
b11 Y
b11 :
b11 C
b11 F
b11 W
b110001111011000000010001000 0
b110001111011000000010001000 a
b110001111011000000010001000 -
b1100 $
b1100 R
b1100 h
b1 &
b1 A
b1 e
b11 ;
b11 ?
b11 @
b1 %
b1 G
b1 T
b1 c
b100 '
b100 B
b100 S
b101000 3
b101000 K
b101000 b
b1100 g
b1111 f
b110000000100010 (
b110000000100010 \
b110000000100010 d
b110000000100010 [
b100010 =
b1111 P
b1100 O
b101000 /
b101000 _
b101000 `
b1100011110110000000100010 7
b1100011110110000000100010 J
b11000000010110000 1
b11000000010110000 ^
b101000 .
b101000 ]
b100100 2
b100100 I
b100100 L
b100100 M
1!
#200000
0!
